{
 "pages": [
  {
   "name": "page1",
   "elements": [
    {
     "type": "radiogroup",
     "name": "Did you have contact with an infected person?",
     "choices": [
      {
       "value": "item1",
       "text": "yes"
      },
      {
       "value": "item2",
       "text": "no"
      }
     ]
    },
    {
     "type": "radiogroup",
     "name": "question1",
     "title": "Do you show symptoms?",
     "choices": [
      {
       "value": "item1",
       "text": "yes"
      },
      {
       "value": "item2",
       "text": "no"
      }
     ]
    },
    {
     "type": "text",
     "name": "question2",
     "visibleIf": "{question1} = 'item1'",
     "title": "Since when do you show the symptoms mentioned in the last step?",
     "inputType": "date"
    }
   ]
  }
 ],
 "triggers": [
  {
   "type": "skip",
   "gotoName": "question3"
  }
 ]
}
